luechenbresse/__init__.py
luechenbresse/ard-tagesschau.py
luechenbresse/data.py
luechenbresse/dotfolder.py
luechenbresse/feed.py
luechenbresse/ini.py
luechenbresse/mailgun.py
luechenbresse/text.py
luechenbresse/zdf-heute.py
luechenbresse/data/db-core.sql
luechenbresse/data/feeds.json
luechenbresse/data/kill_list.txt
luechenbresse/data/namen.txt
luechenbresse-0.0.6.data/scripts/lb-btci
luechenbresse-0.0.6.data/scripts/luechenbresse
luechenbresse-0.0.6.dist-info/LICENSE
luechenbresse-0.0.6.dist-info/METADATA
luechenbresse-0.0.6.dist-info/WHEEL
luechenbresse-0.0.6.dist-info/top_level.txt
luechenbresse-0.0.6.dist-info/RECORD
