Metadata-Version: 2.1
Name: luechenbresse
Version: 0.0.6
Summary: Scraping Germany
Home-page: https://github.com/turkishmaid/luechenbresse
Author: Sara Ziner
License: MIT
Platform: UNKNOWN
Classifier: Programming Language :: Python :: 3
Classifier: License :: OSI Approved :: MIT License
Classifier: Operating System :: OS Independent
Requires-Python: >=3.7
Requires-Dist: requests
Requires-Dist: feedparser
Requires-Dist: bs4
Requires-Dist: docopt
